mcp_sqlite_tool/__init__.py
mcp_sqlite_tool/__main__.py
mcp_sqlite_tool-0.1.2.dist-info/licenses/LICENSE
mcp_sqlite_tool-0.1.2.dist-info/METADATA
mcp_sqlite_tool-0.1.2.dist-info/WHEEL
mcp_sqlite_tool-0.1.2.dist-info/entry_points.txt
mcp_sqlite_tool-0.1.2.dist-info/top_level.txt
mcp_sqlite_tool-0.1.2.dist-info/RECORD
