Metadata-Version: 2.4
Name: mcp-sqlite-tool
Version: 0.1.2
Summary: An MCP server that provides AI with direct access to SQLite databases.
Author-email: mrbeandev <mrbeandev@gmail.com>
Classifier: Programming Language :: Python :: 3
Classifier: License :: OSI Approved :: MIT License
Classifier: Operating System :: OS Independent
Requires-Python: >=3.10
License-File: LICENSE
Requires-Dist: mcp[cli]
Dynamic: license-file
